.bumpversion.cfg
CONTRIBUTING.rst
LICENSE
MANIFEST.in
README.rst
setup.cfg
setup.py
MolVS.egg-info/PKG-INFO
MolVS.egg-info/SOURCES.txt
MolVS.egg-info/dependency_links.txt
MolVS.egg-info/entry_points.txt
MolVS.egg-info/not-zip-safe
MolVS.egg-info/requires.txt
MolVS.egg-info/top_level.txt
docs/.DS_Store
docs/Makefile
docs/source/.DS_Store
docs/source/api.rst
docs/source/conf.py
docs/source/index.rst
docs/source/_images/mol1.png
docs/source/_images/mol1s.png
docs/source/guide/.DS_Store
docs/source/guide/charge.rst
docs/source/guide/cli.rst
docs/source/guide/contributing.rst
docs/source/guide/fragment.rst
docs/source/guide/gettingstarted.rst
docs/source/guide/install.rst
docs/source/guide/intro.rst
docs/source/guide/standardize.rst
docs/source/guide/tautomer.rst
docs/source/guide/validate.rst
molvs/__init__.py
molvs/charge.py
molvs/cli.py
molvs/errors.py
molvs/fragment.py
molvs/metal.py
molvs/normalize.py
molvs/resonance.py
molvs/standardize.py
molvs/tautomer.py
molvs/utils.py
molvs/validate.py
molvs/validations.py
tests/__init__.py
tests/test_charge.py
tests/test_fragment.py
tests/test_metal.py
tests/test_normalize.py
tests/test_resonance.py
tests/test_standardize.py
tests/test_tautomer.py
tests/test_validate.py